{"active_chip": null, "automatic_subs": [{"entry": 3975670, "element_in": 419, "element_out": 36, "event": 20}], "entry_history": {"event": 20, "points": 86, "total_points": 1184, "rank": 966965, "rank_sort": 981175, "overall_rank": 199522, "percentile_rank": null, "bank": 0, "value": 1034, "event_transfers": 2, "event_transfers_cost": 4, "points_on_bench": 7}, "picks": [{"element": 524, "position": 1, "multiplier": 1, "is_captain": false, "is_vice_captain": false}, {"element": 419, "position": 2, "multiplier": 1, "is_captain": false, "is_vice_captain": false}, {"element": 290, "position": 3, "multiplier": 1, "is_captain": false, "is_vice_captain": false}, {"element": 20, "position": 4, "multiplier": 1, "is_captain": false, "is_vice_captain": false}, {"element": 362, "position": 5, "multiplier": 1, "is_captain": false, "is_vice_captain": false}, {"element": 19, "position": 6, "multiplier": 1, "is_captain": false, "is_vice_captain": false}, {"element": 516, "position": 7, "multiplier": 1, "is_captain": false, "is_vice_captain": false}, {"element": 308, "position": 8, "multiplier": 1, "is_captain": false, "is_vice_captain": false}, {"element": 60, "position": 9, "multiplier": 1, "is_captain": false, "is_vice_captain": true}, {"element": 343, "position": 10, "multiplier": 2, "is_captain": true, "is_vice_captain": false}, {"element": 85, "position": 11, "multiplier": 1, "is_captain": false, "is_vice_captain": false}, {"element": 77, "position": 12, "multiplier": 0, "is_captain": false, "is_vice_captain": false}, {"element": 412, "position": 13, "multiplier": 0, "is_captain": false, "is_vice_captain": false}, {"element": 511, "position": 14, "multiplier": 0, "is_captain": false, "is_vice_captain": false}, {"element": 36, "position": 15, "multiplier": 0, "is_captain": false, "is_vice_captain": false}]}