{"active_chip": "wildcard", "automatic_subs": [], "entry_history": {"event": 2, "points": 43, "total_points": 105, "rank": 4855376, "rank_sort": 4861406, "overall_rank": 4625077, "percentile_rank": null, "bank": 15, "value": 1005, "event_transfers": 0, "event_transfers_cost": 0, "points_on_bench": 19}, "picks": [{"element": 145, "position": 1, "multiplier": 1, "is_captain": false, "is_vice_captain": false}, {"element": 20, "position": 2, "multiplier": 1, "is_captain": false, "is_vice_captain": false}, {"element": 195, "position": 3, "multiplier": 1, "is_captain": false, "is_vice_captain": false}, {"element": 131, "position": 4, "multiplier": 1, "is_captain": false, "is_vice_captain": false}, {"element": 19, "position": 5, "multiplier": 2, "is_captain": true, "is_vice_captain": false}, {"element": 599, "position": 6, "multiplier": 1, "is_captain": false, "is_vice_captain": false}, {"element": 396, "position": 7, "multiplier": 1, "is_captain": false, "is_vice_captain": false}, {"element": 303, "position": 8, "multiplier": 1, "is_captain": false, "is_vice_captain": false}, {"element": 135, "position": 9, "multiplier": 1, "is_captain": false, "is_vice_captain": true}, {"element": 211, "position": 10, "multiplier": 1, "is_captain": false, "is_vice_captain": false}, {"element": 355, "position": 11, "multiplier": 1, "is_captain": false, "is_vice_captain": false}, {"element": 524, "position": 12, "multiplier": 0, "is_captain": false, "is_vice_captain": false}, {"element": 353, "position": 13, "multiplier": 0, "is_captain": false, "is_vice_captain": false}, {"element": 342, "position": 14, "multiplier": 0, "is_captain": false, "is_vice_captain": false}, {"element": 473, "position": 15, "multiplier": 0, "is_captain": false, "is_vice_captain": false}]}