{"current": [{"event": 1, "points": 63, "total_points": 63, "rank": 4664772, "rank_sort": 4686168, "overall_rank": 4664773, "bank": 10, "value": 1000, "event_transfers": 0, "event_transfers_cost": 0, "points_on_bench": 5}, {"event": 2, "points": 53, "total_points": 112, "rank": 2173111, "rank_sort": 2175829, "overall_rank": 3697840, "bank": 35, "value": 1003, "event_transfers": 2, "event_transfers_cost": 4, "points_on_bench": 9}, {"event": 3, "points": 44, "total_points": 156, "rank": 4258349, "rank_sort": 4265832, "overall_rank": 3527573, "bank": 13, "value": 1010, "event_transfers": 0, "event_transfers_cost": 0, "points_on_bench": 20}, {"event": 4, "points": 71, "total_points": 227, "rank": 5541804, "rank_sort": 5550627, "overall_rank": 3808758, "bank": 13, "value": 1015, "event_transfers": 0, "event_transfers_cost": 0, "points_on_bench": 8}, {"event": 5, "points": 57, "total_points": 284, "rank": 852231, "rank_sort": 857068, "overall_rank": 2423179, "bank": 15, "value": 1016, "event_transfers": 1, "event_transfers_cost": 0, "points_on_bench": 5}, {"event": 6, "points": 63, "total_points": 347, "rank": 6450795, "rank_sort": 6456075, "overall_rank": 3250903, "bank": 17, "value": 1016, "event_transfers": 2, "event_transfers_cost": 0, "points_on_bench": 5}, {"event": 7, "points": 57, "total_points": 404, "rank": 2730903, "rank_sort": 2737468, "overall_rank": 2571496, "bank": 2, "value": 1021, "event_transfers": 1, "event_transfers_cost": 0, "points_on_bench": 10}, {"event": 8, "points": 39, "total_points": 439, "rank": 6806743, "rank_sort": 6813422, "overall_rank": 3353627, "bank": 15, "value": 1022, "event_transfers": 2, "event_transfers_cost": 4, "points_on_bench": 1}, {"event": 9, "points": 78, "total_points": 517, "rank": 2697757, "rank_sort": 2707869, "overall_rank": 2853419, "bank": 15, "value": 1022, "event_transfers": 0, "event_transfers_cost": 0, "points_on_bench": 3}, {"event": 10, "points": 56, "total_points": 573, "rank": 8268790, "rank_sort": 8273619, "overall_rank": 3567484, "bank": 7, "value": 1025, "event_transfers": 2, "event_transfers_cost": 0, "points_on_bench": 4}, {"event": 11, "points": 36, "total_points": 609, "rank": 3213930, "rank_sort": 3224257, "overall_rank": 3266392, "bank": 3, "value": 1030, "event_transfers": 1, "event_transfers_cost": 0, "points_on_bench": 12}, {"event": 12, "points": 73, "total_points": 682, "rank": 2810178, "rank_sort": 2819127, "overall_rank": 2879759, "bank": 1, "value": 1036, "event_transfers": 1, "event_transfers_cost": 0, "points_on_bench": 11}, {"event": 13, "points": 57, "total_points": 739, "rank": 1283677, "rank_sort": 1290524, "overall_rank": 2333719, "bank": 1, "value": 1041, "event_transfers": 0, "event_transfers_cost": 0, "points_on_bench": 2}, {"event": 14, "points": 65, "total_points": 800, "rank": 2021048, "rank_sort": 2023072, "overall_rank": 2175998, "bank": 3, "value": 1036, "event_transfers": 3, "event_transfers_cost": 4, "points_on_bench": 9}, {"event": 15, "points": 45, "total_points": 845, "rank": 1462944, "rank_sort": 1469677, "overall_rank": 1741686, "bank": 2, "value": 1038, "event_transfers": 1, "event_transfers_cost": 0, "points_on_bench": 3}, {"event": 16, "points": 46, "total_points": 891, "rank": 3864609, "rank_sort": 3873999, "overall_rank": 1744433, "bank": 21, "value": 1038, "event_transfers": 1, "event_transfers_cost": 0, "points_on_bench": 0}, {"event": 17, "points": 50, "total_points": 937, "rank": 3785412, "rank_sort": 3792830, "overall_rank": 1874488, "bank": 57, "value": 1040, "event_transfers": 2, "event_transfers_cost": 4, "points_on_bench": 0}, {"event": 18, "points": 32, "total_points": 965, "rank": 6560511, "rank_sort": 6564873, "overall_rank": 2401769, "bank": 52, "value": 1042, "event_transfers": 2, "event_transfers_cost": 4, "points_on_bench": 10}, {"event": 19, "points": 39, "total_points": 1000, "rank": 4902373, "rank_sort": 4909685, "overall_rank": 2582147, "bank": 11, "value": 1046, "event_transfers": 2, "event_transfers_cost": 4, "points_on_bench": 12}, {"event": 20, "points": 74, "total_points": 1074, "rank": 2668891, "rank_sort": 2675799, "overall_rank": 2419931, "bank": 13, "value": 1047, "event_transfers": 1, "event_transfers_cost": 0, "points_on_bench": 17}, {"event": 21, "points": 19, "total_points": 1093, "rank": 5488699, "rank_sort": 5493050, "overall_rank": 2565788, "bank": 68, "value": 1050, "event_transfers": 1, "event_transfers_cost": 0, "points_on_bench": 18}], "past": [{"season_name": "2011/12", "total_points": 1980, "rank": 206136}, {"season_name": "2012/13", "total_points": 1968, "rank": 310035}, {"season_name": "2013/14", "total_points": 2107, "rank": 617789}, {"season_name": "2014/15", "total_points": 1937, "rank": 423852}, {"season_name": "2015/16", "total_points": 2068, "rank": 332409}, {"season_name": "2016/17", "total_points": 1951, "rank": 860439}, {"season_name": "2017/18", "total_points": 2169, "rank": 204289}, {"season_name": "2018/19", "total_points": 2175, "rank": 372894}, {"season_name": "2019/20", "total_points": 2227, "rank": 196077}, {"season_name": "2020/21", "total_points": 2241, "rank": 652147}, {"season_name": "2021/22", "total_points": 2053, "rank": 2313986}, {"season_name": "2022/23", "total_points": 2400, "rank": 652553}], "chips": [{"name": "wildcard", "time": "2023-08-19T16:43:38.713944Z", "event": 3}]}